{
    "word": "acclaiming",
    "meaning_cases": [
        {
            "word_type_cases": [
                {
                    "head_content": {
                        "word_type": "_",
                        "ipa": {
                            "uk": [],
                            "us": [],
                            "uk_other_tense": [],
                            "us_other_tense": [],
                            "other_tense": ""
                        }
                    },
                    "body_content": [
                        {
                            "explanation": "present participle of \nacclaim ",
                            "examples": []
                        }
                    ]
                }
            ]
        },
        {
            "word_type_cases": [
                {
                    "head_content": {
                        "word_type": "verb",
                        "ipa": {
                            "uk": [
                                "əˈkleɪm"
                            ],
                            "us": [
                                "əˈkleɪm"
                            ],
                            "uk_other_tense": [],
                            "us_other_tense": [],
                            "other_tense": ""
                        }
                    },
                    "body_content": [
                        {
                            "explanation": "to give public approval and praise: ",
                            "examples": [
                                "She was universally/widely/publicly acclaimed for her contribution to the discovery.",
                                "She is being acclaimed (= publicly recognized) as the greatest dancer of her generation."
                            ]
                        }
                    ]
                }
            ]
        }
    ]
}