{
    "word": "alphanumerically",
    "meaning_cases": [
        {
            "word_type_cases": [
                {
                    "head_content": {
                        "word_type": "adverb",
                        "ipa": {
                            "uk": [
                                "ˌæl.fə.njuːˈmer.ɪ.kəl.i"
                            ],
                            "us": [
                                "ˌæl.fə.nuːˈmer.ɪ.kəl.i"
                            ],
                            "uk_other_tense": [],
                            "us_other_tense": [],
                            "other_tense": ""
                        }
                    },
                    "body_content": [
                        {
                            "explanation": "in a way that contains or uses letters of the alphabet and also numbers: ",
                            "examples": [
                                "Users can sort the table alphanumerically by any column.",
                                "You can generate an alphanumerically ordered list."
                            ]
                        }
                    ]
                }
            ]
        }
    ]
}