{
    "word": "anti-traditional",
    "meaning_cases": [
        {
            "word_type_cases": [
                {
                    "head_content": {
                        "word_type": "adjective",
                        "ipa": {
                            "uk": [
                                "ˌæn.ti.trəˈdɪʃ.ən.əl"
                            ],
                            "us": [
                                "ˌæn.taɪ.trəˈdɪʃ.ən.əl"
                            ],
                            "uk_other_tense": [],
                            "us_other_tense": [],
                            "other_tense": ""
                        }
                    },
                    "body_content": [
                        {
                            "explanation": "opposed to tradition or to traditional ideas: ",
                            "examples": [
                                "His music is sometimes characterised as anti-traditional.",
                                "Anti-traditional ways of thinking have produced some challenges to conservatively minded Christians."
                            ]
                        }
                    ]
                }
            ]
        }
    ]
}