{
    "word": "asmr",
    "meaning_cases": [
        {
            "word_type_cases": [
                {
                    "head_content": {
                        "word_type": "noun",
                        "ipa": {
                            "uk": [
                                "ˌeɪ.es.emˈɑːr"
                            ],
                            "us": [
                                "ˌeɪ.es.emˈɑːr"
                            ],
                            "uk_other_tense": [],
                            "us_other_tense": [],
                            "other_tense": ""
                        }
                    },
                    "body_content": [
                        {
                            "explanation": "abbreviation for autonomous sensory meridian response: a pleasant tingling feeling that some people experience on their skin, especially on the head and neck, especially when they hear certain soft sounds such as whispering or brushing: ",
                            "examples": [
                                "The sensation of ASMR has been described as being like a mild electrical current. ",
                                "There are hundreds of ASMR videos online that are supposed to help you relax."
                            ]
                        }
                    ]
                }
            ]
        }
    ]
}