{
    "word": "bible",
    "meaning_cases": [
        {
            "word_type_cases": [
                {
                    "head_content": {
                        "word_type": "noun",
                        "ipa": {
                            "uk": [
                                "ˈbaɪ.bəl"
                            ],
                            "us": [
                                "ˈbaɪ.bəl"
                            ],
                            "uk_other_tense": [],
                            "us_other_tense": [],
                            "other_tense": ""
                        }
                    },
                    "body_content": [
                        {
                            "explanation": "(a copy of) the holy book of the Christian religion consisting of the Old and New Testaments, or the holy book of the Jewish religion consisting of the Law, the Prophets, and the Writings: ",
                            "examples": [
                                "In the Bible it says that Adam and Eve were the first human beings.",
                                "Her parents gave her a bible when she was a young child.",
                                "Bible-reading classes are held in the church hall every Thursday evening."
                            ]
                        },
                        {
                            "explanation": "a book, magazine, etc. that gives important advice and information about a particular subject: ",
                            "examples": [
                                "Vogue magazine quickly became the bible of fashionable women."
                            ]
                        }
                    ]
                }
            ]
        }
    ]
}