{
    "word": "chaining",
    "meaning_cases": [
        {
            "word_type_cases": [
                {
                    "head_content": {
                        "word_type": "_",
                        "ipa": {
                            "uk": [],
                            "us": [],
                            "uk_other_tense": [],
                            "us_other_tense": [],
                            "other_tense": ""
                        }
                    },
                    "body_content": [
                        {
                            "explanation": "present participle of \nchain ",
                            "examples": []
                        }
                    ]
                }
            ]
        },
        {
            "word_type_cases": [
                {
                    "head_content": {
                        "word_type": "verb",
                        "ipa": {
                            "uk": [
                                "tʃeɪn"
                            ],
                            "us": [
                                "tʃeɪn"
                            ],
                            "uk_other_tense": [],
                            "us_other_tense": [],
                            "other_tense": ""
                        }
                    },
                    "body_content": [
                        {
                            "explanation": "to fasten someone or something using a chain: ",
                            "examples": [
                                "It's so cruel to keep a pony chained up like that all the time.",
                                "They chained themselves to lampposts in protest at the judge's decision.",
                                "I don't want a job where I'm chained to a desk for eight hours a day."
                            ]
                        }
                    ]
                }
            ]
        }
    ]
}