{
    "word": "championing",
    "meaning_cases": [
        {
            "word_type_cases": [
                {
                    "head_content": {
                        "word_type": "_",
                        "ipa": {
                            "uk": [],
                            "us": [],
                            "uk_other_tense": [],
                            "us_other_tense": [],
                            "other_tense": ""
                        }
                    },
                    "body_content": [
                        {
                            "explanation": "present participle of \nchampion ",
                            "examples": []
                        }
                    ]
                }
            ]
        },
        {
            "word_type_cases": [
                {
                    "head_content": {
                        "word_type": "verb",
                        "ipa": {
                            "uk": [
                                "ˈtʃæm.pi.ən"
                            ],
                            "us": [
                                "ˈtʃæm.pi.ən"
                            ],
                            "uk_other_tense": [],
                            "us_other_tense": [],
                            "other_tense": ""
                        }
                    },
                    "body_content": [
                        {
                            "explanation": "to support, defend, or fight for a person, belief, right, or principle enthusiastically: ",
                            "examples": [
                                "He has championed constitutional reform for many years."
                            ]
                        }
                    ]
                }
            ]
        }
    ]
}