{
    "word": "connect",
    "meaning_cases": [
        {
            "word_type_cases": [
                {
                    "head_content": {
                        "word_type": "verb",
                        "ipa": {
                            "uk": [
                                "kəˈnekt"
                            ],
                            "us": [
                                "kəˈnekt"
                            ],
                            "uk_other_tense": [],
                            "us_other_tense": [],
                            "other_tense": ""
                        }
                    },
                    "body_content": [
                        {
                            "explanation": "to join or be joined with something else: ",
                            "examples": [
                                "Can I connect my printer to your computer?",
                                "Where does the stove connect (up) to the electricity?",
                                "Has the phone/electricity/gas/internet been connected (= switched on or joined to the main supply) in your new place yet?"
                            ]
                        },
                        {
                            "explanation": "to consider or show a person or thing to be related to someone or something else: ",
                            "examples": [
                                "She's an actress I connect with the theatre rather than films.",
                                "Police are connecting the break-in with other recent thefts in the area."
                            ]
                        },
                        {
                            "explanation": "to feel close to someone or have a good relationship with them: ",
                            "examples": [
                                "She has a remarkable ability to connect with a wide variety of people.",
                                "We just didn't connect."
                            ]
                        },
                        {
                            "explanation": "to make it possible for you to speak to someone else by phone: ",
                            "examples": [
                                "Could you connect me with/to a number in Paris, please? I'm not getting through."
                            ]
                        },
                        {
                            "explanation": "If two buses, trains, etc. connect, they arrive at times that allow passengers to get off one and onto another: ",
                            "examples": [
                                "Your flight arrives at 12.30, when it connects with a bus service to your hotel.",
                                "There's a connecting train service between the airport and the city."
                            ]
                        }
                    ]
                }
            ]
        }
    ]
}