{
    "word": "dabbler",
    "meaning_cases": [
        {
            "word_type_cases": [
                {
                    "head_content": {
                        "word_type": "noun",
                        "ipa": {
                            "uk": [
                                "ˈdæb.lər"
                            ],
                            "us": [
                                "ˈdæb.lɚ"
                            ],
                            "uk_other_tense": [],
                            "us_other_tense": [],
                            "other_tense": ""
                        }
                    },
                    "body_content": [
                        {
                            "explanation": "someone who takes a slight and not very serious interest in a subject, or tries a particular activity for a short period: ",
                            "examples": [
                                "They are dabblers in African music rather than experts.",
                                "I'm not a real painter - just a dabbler."
                            ]
                        }
                    ]
                }
            ]
        }
    ]
}