{
    "word": "deconditioned",
    "meaning_cases": [
        {
            "word_type_cases": [
                {
                    "head_content": {
                        "word_type": "adjective",
                        "ipa": {
                            "uk": [
                                "ˌdiː.kənˈdɪʃ.ənd"
                            ],
                            "us": [
                                "ˌdiː.kənˈdɪʃ.ənd"
                            ],
                            "uk_other_tense": [],
                            "us_other_tense": [],
                            "other_tense": ""
                        }
                    },
                    "body_content": [
                        {
                            "explanation": "having lost physical strength through being ill, injured, or not active: ",
                            "examples": [
                                "When muscle mass is lost it is difficult to regain, therefore it is very important to avoid becoming deconditioned through inactivity.",
                                "In deconditioned patients, the resting heart rate may be high."
                            ]
                        }
                    ]
                }
            ]
        }
    ]
}