{
    "word": "delamination",
    "meaning_cases": [
        {
            "word_type_cases": [
                {
                    "head_content": {
                        "word_type": "noun",
                        "ipa": {
                            "uk": [
                                "ˌdiː.læm.ɪˈneɪ.ʃən"
                            ],
                            "us": [
                                "ˌdiː.læm.əˈneɪ.ʃən"
                            ],
                            "uk_other_tense": [],
                            "us_other_tense": [],
                            "other_tense": ""
                        }
                    },
                    "body_content": [
                        {
                            "explanation": "the process of a material breaking or being broken into thin layers, or an example of this: ",
                            "examples": [
                                "Any moisture in the material would certainly cause delamination and very expensive damage. ",
                                "These defects, such as bubbles, cracks, and delaminations, are not necessarily visible, even under a microscope.",
                                "The skipper pulled out of the race to fix delamination problems with the boat."
                            ]
                        }
                    ]
                }
            ]
        }
    ]
}