{
    "word": "documenting",
    "meaning_cases": [
        {
            "word_type_cases": [
                {
                    "head_content": {
                        "word_type": "_",
                        "ipa": {
                            "uk": [],
                            "us": [],
                            "uk_other_tense": [],
                            "us_other_tense": [],
                            "other_tense": ""
                        }
                    },
                    "body_content": [
                        {
                            "explanation": "present participle of \ndocument ",
                            "examples": []
                        }
                    ]
                }
            ]
        },
        {
            "word_type_cases": [
                {
                    "head_content": {
                        "word_type": "verb",
                        "ipa": {
                            "uk": [
                                "ˈdɒk.jə.ment"
                            ],
                            "us": [
                                "ˈdɑː.kjə.ment"
                            ],
                            "uk_other_tense": [],
                            "us_other_tense": [],
                            "other_tense": ""
                        }
                    },
                    "body_content": [
                        {
                            "explanation": "to record the details of an event, a process, etc.: ",
                            "examples": [
                                "His interest in cars has been well-documented (= recorded and written about) by the media."
                            ]
                        }
                    ]
                }
            ]
        }
    ]
}