{
    "word": "eye drop",
    "meaning_cases": [
        {
            "word_type_cases": [
                {
                    "head_content": {
                        "word_type": "noun",
                        "ipa": {
                            "uk": [
                                "ˈaɪ ˌdrɒp"
                            ],
                            "us": [
                                "ˈaɪ ˌdrɑːp"
                            ],
                            "uk_other_tense": [],
                            "us_other_tense": [],
                            "other_tense": ""
                        }
                    },
                    "body_content": [
                        {
                            "explanation": "liquid medicine put into the eyes, for example to cure an infection or to stop the eyes from feeling sore: ",
                            "examples": [
                                "Glaucoma can be treated with laser surgery or eye drops.",
                                "The eyedrops can be used to soothe itchy eyes.",
                                "Her doctor said she should continue with the eye-drops and avoid eye strain."
                            ]
                        }
                    ]
                }
            ]
        }
    ]
}