{
    "word": "foiling",
    "meaning_cases": [
        {
            "word_type_cases": [
                {
                    "head_content": {
                        "word_type": "_",
                        "ipa": {
                            "uk": [],
                            "us": [],
                            "uk_other_tense": [],
                            "us_other_tense": [],
                            "other_tense": ""
                        }
                    },
                    "body_content": [
                        {
                            "explanation": "present participle of \nfoil ",
                            "examples": []
                        }
                    ]
                }
            ]
        },
        {
            "word_type_cases": [
                {
                    "head_content": {
                        "word_type": "verb",
                        "ipa": {
                            "uk": [
                                "fɔɪl"
                            ],
                            "us": [
                                "fɔɪl"
                            ],
                            "uk_other_tense": [],
                            "us_other_tense": [],
                            "other_tense": ""
                        }
                    },
                    "body_content": [
                        {
                            "explanation": "to prevent someone or something from being successful: ",
                            "examples": [
                                "The prisoners' attempt to escape was foiled at the last minute when police received a tip-off."
                            ]
                        }
                    ]
                }
            ]
        }
    ]
}