{
    "word": "gaucho",
    "meaning_cases": [
        {
            "word_type_cases": [
                {
                    "head_content": {
                        "word_type": "noun",
                        "ipa": {
                            "uk": [
                                "ˈɡaʊ.tʃəʊ"
                            ],
                            "us": [
                                "ˈɡaʊ.tʃoʊ"
                            ],
                            "uk_other_tense": [],
                            "us_other_tense": [],
                            "other_tense": "plural"
                        }
                    },
                    "body_content": [
                        {
                            "explanation": "a South American cowboy (= person who takes care of male and female cows)",
                            "examples": []
                        }
                    ]
                }
            ]
        }
    ]
}