{
    "word": "gerund",
    "meaning_cases": [
        {
            "word_type_cases": [
                {
                    "head_content": {
                        "word_type": "noun",
                        "ipa": {
                            "uk": [
                                "ˈdʒer.ənd"
                            ],
                            "us": [
                                "ˈdʒer.ənd"
                            ],
                            "uk_other_tense": [],
                            "us_other_tense": [],
                            "other_tense": ""
                        }
                    },
                    "body_content": [
                        {
                            "explanation": "a word ending in \"-ing\" that is made from a verb and used like a noun: ",
                            "examples": [
                                "In the sentence \"Everyone enjoyed Tyler's singing\", the word \"singing\" is a gerund."
                            ]
                        }
                    ]
                }
            ]
        }
    ]
}