{
    "word": "growler",
    "meaning_cases": [
        {
            "word_type_cases": [
                {
                    "head_content": {
                        "word_type": "noun",
                        "ipa": {
                            "uk": [
                                "ˈɡraʊ.lər"
                            ],
                            "us": [
                                "ˈɡraʊ.lɚ"
                            ],
                            "uk_other_tense": [],
                            "us_other_tense": [],
                            "other_tense": ""
                        }
                    },
                    "body_content": [
                        {
                            "explanation": "a jug or large bottle that can be filled with beer, especially at a brewery (= a place where beer is made). A growler usually contains 64 fluid ounces: ",
                            "examples": [
                                "I stop by once every week or so to get my growler refilled.",
                                "Beer and root beer is brewed at the facility, and half-gallon growlers are sold there. "
                            ]
                        },
                        {
                            "explanation": "someone who makes a growling sound (= a low, rough sound) when they sing or speak: ",
                            "examples": [
                                "I love Tom Waits and this is one of my favourites from the old growler."
                            ]
                        },
                        {
                            "explanation": "a mass of ice in the sea, especially one that has broken off a larger iceberg or glacier: ",
                            "examples": [
                                "He reported hitting a growler, a rogue fragment of iceberg, while doing over 12 knots."
                            ]
                        },
                        {
                            "explanation": "a four-wheeled carriage pulled by a horse: ",
                            "examples": [
                                "They were nicknamed growlers because of the noise made by their iron wheels."
                            ]
                        }
                    ]
                }
            ]
        }
    ]
}