{
    "word": "hob",
    "meaning_cases": [
        {
            "word_type_cases": [
                {
                    "head_content": {
                        "word_type": "noun",
                        "ipa": {
                            "uk": [
                                "hɒb"
                            ],
                            "us": [
                                "hɑːb"
                            ],
                            "uk_other_tense": [],
                            "us_other_tense": [],
                            "other_tense": ""
                        }
                    },
                    "body_content": [
                        {
                            "explanation": "the top part or surface of a cooker on which pans can be heated: ",
                            "examples": [
                                "Most domestic hobs have four gas or electric rings."
                            ]
                        },
                        {
                            "explanation": "in the past, a metal shelf next to a fireplace where pans were heated",
                            "examples": []
                        }
                    ]
                }
            ]
        }
    ]
}