{
    "word": "leftover",
    "meaning_cases": [
        {
            "word_type_cases": [
                {
                    "head_content": {
                        "word_type": "adjective",
                        "ipa": {
                            "uk": [
                                "ˈleftˌəʊ.vər"
                            ],
                            "us": [
                                "ˈlefˌt̬oʊ.vɚ"
                            ],
                            "uk_other_tense": [],
                            "us_other_tense": [],
                            "other_tense": ""
                        }
                    },
                    "body_content": [
                        {
                            "explanation": "A leftover part of something is the part that has not been used or eaten when the other parts have been: ",
                            "examples": [
                                "some leftover chicken from last night's meal"
                            ]
                        }
                    ]
                },
                {
                    "head_content": {
                        "word_type": "noun",
                        "ipa": {
                            "uk": [
                                "ˈleftˌəʊ.vər"
                            ],
                            "us": [
                                "ˈlefˌt̬oʊ.vɚ"
                            ],
                            "uk_other_tense": [],
                            "us_other_tense": [],
                            "other_tense": ""
                        }
                    },
                    "body_content": [
                        {
                            "explanation": "food remaining after a meal: ",
                            "examples": [
                                "This recipe can serve four easily, and the leftovers are just as good eaten cold."
                            ]
                        }
                    ]
                }
            ]
        }
    ]
}