{
    "word": "liberated",
    "meaning_cases": [
        {
            "word_type_cases": [
                {
                    "head_content": {
                        "word_type": "adjective",
                        "ipa": {
                            "uk": [
                                "ˈlɪb.ər.eɪ.tɪd"
                            ],
                            "us": [
                                "ˈlɪb.ə.reɪ.t̬ɪd"
                            ],
                            "uk_other_tense": [],
                            "us_other_tense": [],
                            "other_tense": ""
                        }
                    },
                    "body_content": [
                        {
                            "explanation": "released from a prison or a place where you have been kept : ",
                            "examples": [
                                "The seven liberated prisoners were hailed as heroes by the American public.",
                                "The regiment was composed mainly of newly liberated slaves."
                            ]
                        },
                        {
                            "explanation": "A liberated place is one where the people in it have been given their freedom: ",
                            "examples": [
                                "The footage was taken at a liberated concentration camp.",
                                "He believed that the newly liberated countries should stick together."
                            ]
                        },
                        {
                            "explanation": "no longer having any limits or controls: ",
                            "examples": [
                                "No longer bound by a strict schedule of training and competing, she felt liberated.",
                                "When I dance I feel liberated, like I've left a heavy load behind."
                            ]
                        },
                        {
                            "explanation": "not following traditional ways of behaving or old ideas: ",
                            "examples": [
                                "She's chosen career advancement instead of having children - does that make her a liberated woman?",
                                "Scandinavia has some of the most liberated and tolerant countries in Europe."
                            ]
                        }
                    ]
                }
            ]
        }
    ]
}