{
    "word": "love match",
    "meaning_cases": [
        {
            "word_type_cases": [
                {
                    "head_content": {
                        "word_type": "noun",
                        "ipa": {
                            "uk": [
                                "ˈlʌv ˌmætʃ"
                            ],
                            "us": [
                                "ˈlʌv ˌmætʃ"
                            ],
                            "uk_other_tense": [],
                            "us_other_tense": [],
                            "other_tense": ""
                        }
                    },
                    "body_content": [
                        {
                            "explanation": "a marriage or relationship between two people who love each other very much",
                            "examples": []
                        }
                    ]
                }
            ]
        }
    ]
}