{
    "word": "moment",
    "meaning_cases": [
        {
            "word_type_cases": [
                {
                    "head_content": {
                        "word_type": "noun",
                        "ipa": {
                            "uk": [
                                "ˈməʊ.mənt"
                            ],
                            "us": [
                                "ˈmoʊ.mənt"
                            ],
                            "uk_other_tense": [],
                            "us_other_tense": [],
                            "other_tense": ""
                        }
                    },
                    "body_content": [
                        {
                            "explanation": "a very short period of time: ",
                            "examples": [
                                "Can you wait a moment?",
                                "I'll be ready in just a moment.",
                                "A car drew up outside and a few moments later the doorbell rang.",
                                "I'm expecting her to come at any moment (= very soon).",
                                "Have you got a moment (= are you busy or do you have time to speak to me)?"
                            ]
                        },
                        {
                            "explanation": "a particular time or occasion: ",
                            "examples": [
                                "When would be the best moment to tell the family?",
                                "Don't leave it to/till the last moment (= the latest time possible).",
                                "If you want a private conversation with her you'll have to choose your moment (= find a suitable time).",
                                "The moment (that) (= as soon as) I get the money I'll send the ticket."
                            ]
                        },
                        {
                            "explanation": "now: ",
                            "examples": [
                                "Sorry, she's not here at the moment."
                            ]
                        },
                        {
                            "explanation": "If you do something for the moment, you are doing it now, but might do something different in the future: ",
                            "examples": [
                                "Let's keep doing what we agreed for the moment."
                            ]
                        },
                        {
                            "explanation": "now: ",
                            "examples": [
                                "I can give no information at this precise moment in time."
                            ]
                        },
                        {
                            "explanation": "very important: ",
                            "examples": [
                                "a decision of great moment"
                            ]
                        }
                    ]
                }
            ]
        }
    ]
}