{
    "word": "morbid",
    "meaning_cases": [
        {
            "word_type_cases": [
                {
                    "head_content": {
                        "word_type": "adjective",
                        "ipa": {
                            "uk": [
                                "ˈmɔː.bɪd"
                            ],
                            "us": [
                                "ˈmɔːr.bɪd"
                            ],
                            "uk_other_tense": [],
                            "us_other_tense": [],
                            "other_tense": ""
                        }
                    },
                    "body_content": [
                        {
                            "explanation": "too interested in unpleasant subjects, especially death: ",
                            "examples": [
                                "a morbid fascination with death"
                            ]
                        },
                        {
                            "explanation": "relating to or caused by disease: ",
                            "examples": [
                                "She had to have gastric bypass surgery to avoid dying from morbid obesity.",
                                "Pathological anatomy (or morbid anatomy) is the study of diseased organs."
                            ]
                        }
                    ]
                }
            ]
        }
    ]
}