{
    "word": "nonsensical",
    "meaning_cases": [
        {
            "word_type_cases": [
                {
                    "head_content": {
                        "word_type": "adjective",
                        "ipa": {
                            "uk": [
                                "ˌnɒnˈsen.sɪ.kəl"
                            ],
                            "us": [
                                "ˌnɑːnˈsen.sɪ.kəl"
                            ],
                            "uk_other_tense": [],
                            "us_other_tense": [],
                            "other_tense": ""
                        }
                    },
                    "body_content": [
                        {
                            "explanation": "silly or stupid: ",
                            "examples": [
                                "It's nonsensical to blame all the world's troubles on one man.",
                                "Their methods of assessment produce nonsensical results."
                            ]
                        }
                    ]
                }
            ]
        }
    ]
}