{
    "word": "out-debate",
    "meaning_cases": [
        {
            "word_type_cases": [
                {
                    "head_content": {
                        "word_type": "verb",
                        "ipa": {
                            "uk": [
                                "ˌaʊt.dɪˈbeɪt"
                            ],
                            "us": [
                                "ˌaʊt.dɪˈbeɪt"
                            ],
                            "uk_other_tense": [],
                            "us_other_tense": [],
                            "other_tense": ""
                        }
                    },
                    "body_content": [
                        {
                            "explanation": "to debate a subject (= discuss it formally) better than someone else: ",
                            "examples": [
                                "Although out-debated by the opposition leader, the Prime Minister still won the vote.",
                                "As a trained lawyer, she could outdebate anyone."
                            ]
                        }
                    ]
                }
            ]
        }
    ]
}