{
    "word": "pharaonic",
    "meaning_cases": [
        {
            "word_type_cases": [
                {
                    "head_content": {
                        "word_type": "adjective",
                        "ipa": {
                            "uk": [
                                "fəˈrɒn.ɪk",
                                "ˌfeə.reɪˈɒn.ɪk"
                            ],
                            "us": [
                                "feˈrɑː.nɪk",
                                "ˌfer.iˈɑː.nɪk"
                            ],
                            "uk_other_tense": [],
                            "us_other_tense": [],
                            "other_tense": ""
                        }
                    },
                    "body_content": [
                        {
                            "explanation": "belonging or relating to a pharaoh (= a king of ancient Egypt): ",
                            "examples": [
                                "We visited Luxor and marvelled at the pharaonic monuments.",
                                "The museum has hundreds of items of Pharaonic art on display."
                            ]
                        }
                    ]
                }
            ]
        }
    ]
}