{
    "word": "re-engage",
    "meaning_cases": [
        {
            "word_type_cases": [
                {
                    "head_content": {
                        "word_type": "verb",
                        "ipa": {
                            "uk": [
                                "ˌriː.ɪnˈɡeɪdʒ"
                            ],
                            "us": [
                                "ˌriː.ɪnˈɡeɪdʒ"
                            ],
                            "uk_other_tense": [],
                            "us_other_tense": [],
                            "other_tense": ""
                        }
                    },
                    "body_content": [
                        {
                            "explanation": "to become involved, or have contact, with someone or something again, for a second, third, etc. time: ",
                            "examples": [
                                "The campaign is trying to help former students re-engage with the university.",
                                "Ex-prisoners should be encouraged to reengage in society."
                            ]
                        },
                        {
                            "explanation": "to interest someone in something again for a second, third, etc. time, and keep them thinking about it: ",
                            "examples": [
                                "More straightforward campaigning might just reengage the voting public.",
                                "Environmental groups have to re-engage mainstream Australia."
                            ]
                        },
                        {
                            "explanation": "to engage part of a machine or your body (= make it fit into and move together with another part) again, for a second, third, etc. time: ",
                            "examples": [
                                "Manual override is provided to re-engage the motor.",
                                "During the course of losing weight, I had to re-engage muscles that were engaged automatically before.",
                                "When the throttle is applied, the clutch automatically re-engages."
                            ]
                        },
                        {
                            "explanation": "to employ someone again: ",
                            "examples": [
                                "Why have we re-engaged him on another year's contract?",
                                "She was made redundant in 2020, but was re-engaged in late 2021."
                            ]
                        }
                    ]
                }
            ]
        }
    ]
}