{
    "word": "rorting",
    "meaning_cases": [
        {
            "word_type_cases": [
                {
                    "head_content": {
                        "word_type": "_",
                        "ipa": {
                            "uk": [],
                            "us": [],
                            "uk_other_tense": [],
                            "us_other_tense": [],
                            "other_tense": ""
                        }
                    },
                    "body_content": [
                        {
                            "explanation": "present participle of \nrort ",
                            "examples": []
                        }
                    ]
                }
            ]
        },
        {
            "word_type_cases": [
                {
                    "head_content": {
                        "word_type": "verb",
                        "ipa": {
                            "uk": [
                                "rɔːt"
                            ],
                            "us": [
                                "rɔːrt"
                            ],
                            "uk_other_tense": [],
                            "us_other_tense": [],
                            "other_tense": ""
                        }
                    },
                    "body_content": [
                        {
                            "explanation": "to take unfair advantage of a public service: ",
                            "examples": [
                                "Gary's been rorting the system, getting both a student allowance and unemployment benefit."
                            ]
                        }
                    ]
                }
            ]
        }
    ]
}