{
    "word": "servilely",
    "meaning_cases": [
        {
            "word_type_cases": [
                {
                    "head_content": {
                        "word_type": "adverb",
                        "ipa": {
                            "uk": [
                                "ˈsɜː.vaɪl.li"
                            ],
                            "us": [
                                "ˈsɝː.vaɪl.li"
                            ],
                            "uk_other_tense": [],
                            "us_other_tense": [],
                            "other_tense": ""
                        }
                    },
                    "body_content": [
                        {
                            "explanation": "in a way that shows that you are too eager to serve and please someone else and do not have much respect for yourself : ",
                            "examples": [
                                "His colleagues lost a lot of respect for him for the way he would servilely flatter the boss. ",
                                "I need an assistant who can listen and do a a good job, not someone to wait on me servilely hand and foot."
                            ]
                        }
                    ]
                }
            ]
        }
    ]
}