{
    "word": "stony",
    "meaning_cases": [
        {
            "word_type_cases": [
                {
                    "head_content": {
                        "word_type": "adjective",
                        "ipa": {
                            "uk": [
                                "ˈstəʊ.ni"
                            ],
                            "us": [
                                "ˈstoʊ.ni"
                            ],
                            "uk_other_tense": [],
                            "us_other_tense": [],
                            "other_tense": ""
                        }
                    },
                    "body_content": [
                        {
                            "explanation": "Stony ground contains a lot of stones: ",
                            "examples": [
                                "The island has several stony beaches which are usually deserted."
                            ]
                        },
                        {
                            "explanation": "A stony expression or way of behaving is one that shows no sympathy or kindness: ",
                            "examples": [
                                "She gave me a stony glare as I walked into the room.",
                                "Most of her comments were met with a stony silence."
                            ]
                        }
                    ]
                }
            ]
        }
    ]
}