{
    "word": "stray",
    "meaning_cases": [
        {
            "word_type_cases": [
                {
                    "head_content": {
                        "word_type": "verb",
                        "ipa": {
                            "uk": [
                                "streɪ"
                            ],
                            "us": [
                                "streɪ"
                            ],
                            "uk_other_tense": [],
                            "us_other_tense": [],
                            "other_tense": ""
                        }
                    },
                    "body_content": [
                        {
                            "explanation": "to travel along a route that was not originally intended, or to move outside a limited area: ",
                            "examples": [
                                "A herd of cattle had strayed into the road.",
                                "They got lost when they strayed too far from the path.",
                                "The ship strayed off course during the storm."
                            ]
                        },
                        {
                            "explanation": "to start thinking or talking about a different subject from the one you should be giving attention to: ",
                            "examples": [
                                "I think we've strayed too far from our original plan.",
                                "Sorry - I've strayed from the subject."
                            ]
                        }
                    ]
                },
                {
                    "head_content": {
                        "word_type": "noun",
                        "ipa": {
                            "uk": [
                                "streɪ"
                            ],
                            "us": [
                                "streɪ"
                            ],
                            "uk_other_tense": [],
                            "us_other_tense": [],
                            "other_tense": ""
                        }
                    },
                    "body_content": [
                        {
                            "explanation": "a pet that no longer has a home or cannot find its home: ",
                            "examples": [
                                "a stray dog",
                                "\"Who owns that cat?\" \"I don't know. I think it must be a stray.\""
                            ]
                        }
                    ]
                },
                {
                    "head_content": {
                        "word_type": "adjective",
                        "ipa": {
                            "uk": [
                                "streɪ"
                            ],
                            "us": [
                                "streɪ"
                            ],
                            "uk_other_tense": [],
                            "us_other_tense": [],
                            "other_tense": ""
                        }
                    },
                    "body_content": [
                        {
                            "explanation": "Stray things have moved apart from similar things and are not in their expected or intended place: ",
                            "examples": [
                                "There are still a few stray spots of paint on the window pane.",
                                "Several journalists have been killed or injured by stray bullets while reporting on the civil war."
                            ]
                        }
                    ]
                }
            ]
        }
    ]
}