{
    "word": "super-convenient",
    "meaning_cases": [
        {
            "word_type_cases": [
                {
                    "head_content": {
                        "word_type": "adjective",
                        "ipa": {
                            "uk": [
                                "ˌsuː.pə.kənˈviː.ni.ənt"
                            ],
                            "us": [
                                "ˌsuː.pɚ.kənˈviːn.jənt"
                            ],
                            "uk_other_tense": [],
                            "us_other_tense": [],
                            "other_tense": ""
                        }
                    },
                    "body_content": [
                        {
                            "explanation": "very suitable for your purposes and needs, and causing the least difficulty: ",
                            "examples": [
                                "Being able to do your banking from home is super-convenient.",
                                "These compact ovens are superconvenient, and will fit on your kitchen counter."
                            ]
                        },
                        {
                            "explanation": "very near or easy to get to or use: ",
                            "examples": [
                                "The shop is within walking distance of both my house and my work, so it's superconvenient.",
                                "We went there for lunch the other day because it was super convenient."
                            ]
                        }
                    ]
                }
            ]
        }
    ]
}