{
    "word": "tablespoon",
    "meaning_cases": [
        {
            "word_type_cases": [
                {
                    "head_content": {
                        "word_type": "noun",
                        "ipa": {
                            "uk": [
                                "ˈteɪ.bəl.spuːn"
                            ],
                            "us": [
                                "ˈteɪ.bəl.spuːn"
                            ],
                            "uk_other_tense": [],
                            "us_other_tense": [],
                            "other_tense": ""
                        }
                    },
                    "body_content": [
                        {
                            "explanation": "a large spoon used for serving food or the amount that it holds: ",
                            "examples": [
                                "three tablespoons of sugar"
                            ]
                        },
                        {
                            "explanation": "a spoon that contains 15 mililitres, used for measuring food, or the amount that it holds",
                            "examples": []
                        }
                    ]
                }
            ]
        }
    ]
}