{
    "word": "wet macular degeneration",
    "meaning_cases": [
        {
            "word_type_cases": [
                {
                    "head_content": {
                        "word_type": "noun",
                        "ipa": {
                            "uk": [
                                "wet ˌmæk.jə.lə dɪ.dʒen.əˈreɪ.ʃən"
                            ],
                            "us": [
                                "ˈwet ˈmæk.jə.lɚ dɪˌdʒen.əˈreɪ.ʃən"
                            ],
                            "uk_other_tense": [],
                            "us_other_tense": [],
                            "other_tense": ""
                        }
                    },
                    "body_content": [
                        {
                            "explanation": "a disease in older people in which blood vessels leak fluid into the most important part of the retina (= the area at the back of the eye that receives light), making it weaker and leading to problems when looking directly at objects and to loss of sight",
                            "examples": []
                        }
                    ]
                }
            ]
        }
    ]
}